mlpro/__init__.py
mlpro/bf/__init__.py
mlpro/bf/events.py
mlpro/bf/exceptions.py
mlpro/bf/mt.py
mlpro/bf/ops.py
mlpro/bf/various.py
mlpro/bf/control/__init__.py
mlpro/bf/control/basics.py
mlpro/bf/control/controllers/__init__.py
mlpro/bf/control/controllers/hunter.py
mlpro/bf/control/controllers/pid_controller.py
mlpro/bf/control/controlsystems/__init__.py
mlpro/bf/control/controlsystems/basic.py
mlpro/bf/control/controlsystems/cascade.py
mlpro/bf/control/operators/__init__.py
mlpro/bf/control/operators/comparator.py
mlpro/bf/control/operators/converter.py
mlpro/bf/control/operators/integrator.py
mlpro/bf/data/__init__.py
mlpro/bf/data/buffers.py
mlpro/bf/data/cfg_file.py
mlpro/bf/data/datastoring.py
mlpro/bf/datasets/__init__.py
mlpro/bf/datasets/basics.py
mlpro/bf/math/__init__.py
mlpro/bf/math/basics.py
mlpro/bf/math/properties.py
mlpro/bf/math/geometry/__init__.py
mlpro/bf/math/geometry/basics.py
mlpro/bf/math/geometry/crosshair.py
mlpro/bf/math/geometry/hypercuboid.py
mlpro/bf/math/geometry/point.py
mlpro/bf/math/normalizers/__init__.py
mlpro/bf/math/normalizers/basics.py
mlpro/bf/math/normalizers/minmax.py
mlpro/bf/math/normalizers/ztrans.py
mlpro/bf/math/statistics/__init__.py
mlpro/bf/math/statistics/boundaries.py
mlpro/bf/ml/__init__.py
mlpro/bf/ml/basics.py
mlpro/bf/ml/systems/__init__.py
mlpro/bf/ml/systems/basics.py
mlpro/bf/ml/systems/pool/__init__.py
mlpro/bf/physics/__init__.py
mlpro/bf/physics/basics.py
mlpro/bf/physics/unitconverter.py
mlpro/bf/plot/__init__.py
mlpro/bf/plot/basics.py
mlpro/bf/plot/dataplotting.py
mlpro/bf/plot/backends/__init__.py
mlpro/bf/plot/backends/basics.py
mlpro/bf/plot/backends/qtagg.py
mlpro/bf/plot/backends/tkagg.py
mlpro/bf/streams/__init__.py
mlpro/bf/streams/basics.py
mlpro/bf/streams/helpers/__init__.py
mlpro/bf/streams/samplers/__init__.py
mlpro/bf/streams/samplers/min_wise.py
mlpro/bf/streams/samplers/random.py
mlpro/bf/streams/samplers/reservoir_sampling.py
mlpro/bf/streams/samplers/weighted_random.py
mlpro-2.1.0.dist-info/licenses/LICENSE
mlpro-2.1.0.dist-info/METADATA
mlpro-2.1.0.dist-info/WHEEL
mlpro-2.1.0.dist-info/top_level.txt
mlpro-2.1.0.dist-info/RECORD
