Metadata-Version: 2.4
Name: mlpro
Version: 2.1.0
Summary: MLPro - The integrative middleware framework for standardized machine learning
Home-page: https://mlpro.readthedocs.io
Author: MLPro Team
Author-email: mlpro@listen.fh-swf.de
Project-URL: Bug Tracker, https://mlpro.readthedocs.io
Classifier: Programming Language :: Python :: 3
Classifier: License :: OSI Approved :: Apache Software License
Classifier: Operating System :: OS Independent
Requires-Python: >=3.11
License-File: LICENSE
Provides-Extra: full
Requires-Dist: dill>=0.4.0; extra == "full"
Requires-Dist: multiprocess>=0.70.18; extra == "full"
Requires-Dist: numpy>=2.2.5; extra == "full"
Requires-Dist: PySide6>=6.9.0; extra == "full"
Requires-Dist: matplotlib>=3.10.1; extra == "full"
Requires-Dist: scipy>=1.10.1; extra == "full"
Requires-Dist: pandas>=2.1.3; extra == "full"
Dynamic: license-file
